{
	"$schema": "http://schema.management.azure.com/schemas/2015-01-01/deploymentTemplate.json#",
	"contentVersion": "1.0.0.0",
	"parameters": {
		"factoryName": {
			"type": "string",
			"metadata": "Data Factory name",
			"defaultValue": "datafactorykeystone"
		},
		"AzureBlobStorage1_connectionString": {
			"type": "secureString",
			"metadata": "Secure string for 'connectionString' of 'AzureBlobStorage1'"
		},
		"AzureDatabricks1_accessToken": {
			"type": "secureString",
			"metadata": "Secure string for 'accessToken' of 'AzureDatabricks1'"
		},
		"AzureFileStorage1_connectionString": {
			"type": "secureString",
			"metadata": "Secure string for 'connectionString' of 'AzureFileStorage1'"
		},
		"outputSql_connectionString": {
			"type": "secureString",
			"metadata": "Secure string for 'connectionString' of 'outputSql'"
		},
		"AzureDatabricks1_properties_typeProperties_existingClusterId": {
			"type": "string",
			"defaultValue": "0819-010628-v0fq91sj"
		}
	},
	"variables": {
		"factoryId": "[concat('Microsoft.DataFactory/factories/', parameters('factoryName'))]"
	},
	"resources": [
		{
			"name": "[concat(parameters('factoryName'), '/pipeline1')]",
			"type": "Microsoft.DataFactory/factories/pipelines",
			"apiVersion": "2018-06-01",
			"properties": {
				"activities": [
					{
						"name": "Copy data1",
						"type": "Copy",
						"dependsOn": [],
						"policy": {
							"timeout": "7.00:00:00",
							"retry": 0,
							"retryIntervalInSeconds": 30,
							"secureOutput": false,
							"secureInput": false
						},
						"userProperties": [],
						"typeProperties": {
							"source": {
								"type": "ExcelSource",
								"storeSettings": {
									"type": "AzureFileStorageReadSettings",
									"recursive": false,
									"wildcardFileName": "*",
									"enablePartitionDiscovery": false
								}
							},
							"sink": {
								"type": "DelimitedTextSink",
								"storeSettings": {
									"type": "AzureBlobStorageWriteSettings",
									"copyBehavior": "MergeFiles"
								},
								"formatSettings": {
									"type": "DelimitedTextWriteSettings",
									"quoteAllText": true,
									"fileExtension": ".csv"
								}
							},
							"enableStaging": false,
							"translator": {
								"type": "TabularTranslator",
								"typeConversion": true,
								"typeConversionSettings": {
									"allowDataTruncation": true,
									"treatBooleanAsNumber": false
								}
							}
						},
						"inputs": [
							{
								"referenceName": "InputExcel",
								"type": "DatasetReference",
								"parameters": {}
							}
						],
						"outputs": [
							{
								"referenceName": "CSV",
								"type": "DatasetReference",
								"parameters": {}
							}
						]
					},
					{
						"name": "Notebook1",
						"type": "DatabricksNotebook",
						"dependsOn": [
							{
								"activity": "Copy data1",
								"dependencyConditions": [
									"Succeeded"
								]
							}
						],
						"policy": {
							"timeout": "7.00:00:00",
							"retry": 0,
							"retryIntervalInSeconds": 30,
							"secureOutput": false,
							"secureInput": false
						},
						"userProperties": [],
						"typeProperties": {
							"notebookPath": "/Users/chen1421@e.ntu.edu.sg/test2"
						},
						"linkedServiceName": {
							"referenceName": "AzureDatabricks1",
							"type": "LinkedServiceReference"
						}
					}
				],
				"policy": {
					"elapsedTimeMetric": {},
					"cancelAfter": {}
				},
				"annotations": []
			},
			"dependsOn": [
				"[concat(variables('factoryId'), '/datasets/InputExcel')]",
				"[concat(variables('factoryId'), '/datasets/CSV')]",
				"[concat(variables('factoryId'), '/linkedServices/AzureDatabricks1')]"
			]
		},
		{
			"name": "[concat(parameters('factoryName'), '/pipeline1_copy1')]",
			"type": "Microsoft.DataFactory/factories/pipelines",
			"apiVersion": "2018-06-01",
			"properties": {
				"activities": [
					{
						"name": "Copy data1",
						"type": "Copy",
						"dependsOn": [],
						"policy": {
							"timeout": "7.00:00:00",
							"retry": 0,
							"retryIntervalInSeconds": 30,
							"secureOutput": false,
							"secureInput": false
						},
						"userProperties": [],
						"typeProperties": {
							"source": {
								"type": "ExcelSource",
								"storeSettings": {
									"type": "AzureFileStorageReadSettings",
									"recursive": false,
									"wildcardFileName": "*",
									"enablePartitionDiscovery": false
								}
							},
							"sink": {
								"type": "AzureSqlSink",
								"writeBehavior": "upsert",
								"upsertSettings": {
									"useTempDB": true,
									"keys": [
										"Holding_Scenario"
									]
								},
								"sqlWriterUseTableLock": false,
								"disableMetricsCollection": false
							},
							"enableStaging": false,
							"translator": {
								"type": "TabularTranslator",
								"mappings": [
									{
										"source": {
											"name": "Position Scenario Date Adjusted",
											"type": "String",
											"physicalType": "String"
										},
										"sink": {
											"name": "Position_Scenario_Date_Adjusted",
											"type": "DateTime",
											"physicalType": "datetime"
										}
									},
									{
										"source": {
											"name": "FundShortName",
											"type": "String",
											"physicalType": "String"
										},
										"sink": {
											"name": "FundShortName",
											"type": "String",
											"physicalType": "varchar"
										}
									},
									{
										"source": {
											"name": "Hierarchy 3",
											"type": "String",
											"physicalType": "String"
										},
										"sink": {
											"name": "Hierarchy3",
											"type": "String",
											"physicalType": "varchar"
										}
									},
									{
										"source": {
											"name": "Instrument Subtype",
											"type": "String",
											"physicalType": "String"
										},
										"sink": {
											"name": "Instrument_Subtype",
											"type": "String",
											"physicalType": "varchar"
										}
									},
									{
										"source": {
											"name": "BB Yellow Key",
											"type": "String",
											"physicalType": "String"
										},
										"sink": {
											"name": "BB_Yellow_Key",
											"type": "String",
											"physicalType": "varchar"
										}
									},
									{
										"source": {
											"name": "Description",
											"type": "String",
											"physicalType": "String"
										},
										"sink": {
											"name": "Description",
											"type": "String",
											"physicalType": "varchar"
										}
									},
									{
										"source": {
											"name": "Keystone Broad Sector",
											"type": "String",
											"physicalType": "String"
										},
										"sink": {
											"name": "Keystone_Broad_Sector",
											"type": "String",
											"physicalType": "varchar"
										}
									},
									{
										"source": {
											"name": "Keystone Custom Sector",
											"type": "String",
											"physicalType": "String"
										},
										"sink": {
											"name": "Keystone_Custom_Sector",
											"type": "String",
											"physicalType": "varchar"
										}
									},
									{
										"source": {
											"name": "GIC Sector",
											"type": "String",
											"physicalType": "String"
										},
										"sink": {
											"name": "GIC_Sector",
											"type": "String",
											"physicalType": "varchar"
										}
									},
									{
										"source": {
											"name": "GIC Industry Group",
											"type": "String",
											"physicalType": "String"
										},
										"sink": {
											"name": "GIC_Industry_Group",
											"type": "String",
											"physicalType": "varchar"
										}
									},
									{
										"source": {
											"name": "GIC Industry",
											"type": "String",
											"physicalType": "String"
										},
										"sink": {
											"name": "GIC_Industry",
											"type": "String",
											"physicalType": "varchar"
										}
									},
									{
										"source": {
											"name": "Exchange",
											"type": "String",
											"physicalType": "String"
										},
										"sink": {
											"name": "Exchange",
											"type": "String",
											"physicalType": "varchar"
										}
									},
									{
										"source": {
											"name": "Risk Country",
											"type": "String",
											"physicalType": "String"
										},
										"sink": {
											"name": "Risk_Country",
											"type": "String",
											"physicalType": "varchar"
										}
									},
									{
										"source": {
											"name": "Country of Domicile",
											"type": "String",
											"physicalType": "String"
										},
										"sink": {
											"name": "Country_of_Domicile",
											"type": "String",
											"physicalType": "varchar"
										}
									},
									{
										"source": {
											"name": "Country Region",
											"type": "String",
											"physicalType": "String"
										},
										"sink": {
											"name": "Country_Region",
											"type": "String",
											"physicalType": "varchar"
										}
									},
									{
										"source": {
											"name": "Exchange Country Name",
											"type": "String",
											"physicalType": "String"
										},
										"sink": {
											"name": "Exchange_Country_Name",
											"type": "String",
											"physicalType": "varchar"
										}
									},
									{
										"source": {
											"name": "Exchange Country Region",
											"type": "String",
											"physicalType": "String"
										},
										"sink": {
											"name": "Exchange_Country_Region",
											"type": "String",
											"physicalType": "varchar"
										}
									},
									{
										"source": {
											"name": "Notional Quantity",
											"type": "String",
											"physicalType": "String"
										},
										"sink": {
											"name": "Notional_Quantity",
											"type": "Int32",
											"physicalType": "int"
										}
									},
									{
										"source": {
											"name": "Market Price",
											"type": "String",
											"physicalType": "String"
										},
										"sink": {
											"name": "Market_Price",
											"type": "Double",
											"physicalType": "float"
										}
									},
									{
										"source": {
											"name": "$ Position Instrument Market Price",
											"type": "String",
											"physicalType": "String"
										},
										"sink": {
											"name": "Position_Instrument_Market_Price",
											"type": "Double",
											"physicalType": "float"
										}
									},
									{
										"source": {
											"name": "Long/Short Position",
											"type": "String",
											"physicalType": "String"
										},
										"sink": {
											"name": "LongShort_Position",
											"type": "String",
											"physicalType": "varchar"
										}
									},
									{
										"source": {
											"name": "NMV (excl Cash & FX)",
											"type": "String",
											"physicalType": "String"
										},
										"sink": {
											"name": "NMV_excl_Cash_FX",
											"type": "Double",
											"physicalType": "float"
										}
									},
									{
										"source": {
											"name": "GMV (excl Cash & FX)",
											"type": "String",
											"physicalType": "String"
										},
										"sink": {
											"name": "GMV_excl_Cash_FX",
											"type": "Double",
											"physicalType": "float"
										}
									},
									{
										"source": {
											"name": "PBD NMV (excl Cash & FX)",
											"type": "String",
											"physicalType": "String"
										},
										"sink": {
											"name": "PBD_NMV_excl_CashnFX",
											"type": "Double",
											"physicalType": "float"
										}
									},
									{
										"source": {
											"name": "PBD GMV (excl Cash & FX)",
											"type": "String",
											"physicalType": "String"
										},
										"sink": {
											"name": "PBD_GMV_excl_CashnFX",
											"type": "Double",
											"physicalType": "float"
										}
									},
									{
										"source": {
											"name": "$ Daily P&L",
											"type": "String",
											"physicalType": "String"
										},
										"sink": {
											"name": "Daily_PnL",
											"type": "Double",
											"physicalType": "float"
										}
									},
									{
										"source": {
											"name": "AUM",
											"type": "String",
											"physicalType": "String"
										},
										"sink": {
											"name": "AUM",
											"type": "Int32",
											"physicalType": "int"
										}
									},
									{
										"source": {
											"name": "Market Capitalization (mil USD)",
											"type": "String",
											"physicalType": "String"
										},
										"sink": {
											"name": "Market_Capitalization_milUSD",
											"type": "Double",
											"physicalType": "float"
										}
									},
									{
										"source": {
											"name": "Market Cap",
											"type": "String",
											"physicalType": "String"
										},
										"sink": {
											"name": "Market_Cap",
											"type": "Double",
											"physicalType": "float"
										}
									},
									{
										"source": {
											"name": "Daily P&L % NAV",
											"type": "String",
											"physicalType": "String"
										},
										"sink": {
											"name": "Daily_PnL_ptg_NAV",
											"type": "String",
											"physicalType": "varchar"
										}
									},
									{
										"source": {
											"name": "NMV % NAV",
											"type": "String",
											"physicalType": "String"
										},
										"sink": {
											"name": "NMV_ptg_NAV",
											"type": "Double",
											"physicalType": "float"
										}
									},
									{
										"source": {
											"name": "GMV % NAV",
											"type": "String",
											"physicalType": "String"
										},
										"sink": {
											"name": "GMV_ptg_NAV",
											"type": "Double",
											"physicalType": "float"
										}
									},
									{
										"source": {
											"name": "Beta Adj MV (MSCICN)",
											"type": "String",
											"physicalType": "String"
										},
										"sink": {
											"name": "Beta_Adj_MV_MSCICN",
											"type": "Double",
											"physicalType": "float"
										}
									},
									{
										"source": {
											"name": "Beta Adj MV(MSCI ex Japan)",
											"type": "String",
											"physicalType": "String"
										},
										"sink": {
											"name": "Beta_Adj_MV_MSCI_ex_Japan",
											"type": "Double",
											"physicalType": "float"
										}
									},
									{
										"source": {
											"name": "Beta Adj MV (MSCI Asia)",
											"type": "String",
											"physicalType": "String"
										},
										"sink": {
											"name": "Beta_Adj_MV_MSCI_Asia",
											"type": "Double",
											"physicalType": "float"
										}
									},
									{
										"source": {
											"name": "Beta Adj MV (SPX)",
											"type": "String",
											"physicalType": "String"
										},
										"sink": {
											"name": "Beta_Adj_MV_SPX",
											"type": "Double",
											"physicalType": "float"
										}
									},
									{
										"source": {
											"name": "BetaMSCICN",
											"type": "String",
											"physicalType": "String"
										},
										"sink": {
											"name": "Beta_MSCICN",
											"type": "Double",
											"physicalType": "float"
										}
									},
									{
										"source": {
											"name": "Beta MSCI ex Japan",
											"type": "String",
											"physicalType": "String"
										},
										"sink": {
											"name": "Beta_MSCI_ex_Japan",
											"type": "Double",
											"physicalType": "float"
										}
									},
									{
										"source": {
											"name": "Beta MSCI Asia",
											"type": "String",
											"physicalType": "String"
										},
										"sink": {
											"name": "Beta_MSCI_Asia",
											"type": "Double",
											"physicalType": "float"
										}
									},
									{
										"source": {
											"name": "BetaSPX",
											"type": "String",
											"physicalType": "String"
										},
										"sink": {
											"name": "BetaSPX",
											"type": "Double",
											"physicalType": "float"
										}
									},
									{
										"source": {
											"name": "Position Age (From Last Trade Date)",
											"type": "String",
											"physicalType": "String"
										},
										"sink": {
											"name": "Position_Age_From_Last_Trade_Date",
											"type": "Int32",
											"physicalType": "int"
										}
									},
									{
										"source": {
											"name": "Position Age (From First Trade Date)",
											"type": "String",
											"physicalType": "String"
										},
										"sink": {
											"name": "Position_Age_From_First_Trade_Date",
											"type": "Int32",
											"physicalType": "int"
										}
									},
									{
										"source": {
											"name": "Custodian",
											"type": "String",
											"physicalType": "String"
										},
										"sink": {
											"name": "Custodian",
											"type": "String",
											"physicalType": "varchar"
										}
									},
									{
										"source": {
											"name": "Holding Scenario",
											"type": "String",
											"physicalType": "String"
										},
										"sink": {
											"name": "Holding_Scenario",
											"type": "String",
											"physicalType": "varchar"
										}
									},
									{
										"source": {
											"name": "% Price Change",
											"type": "String",
											"physicalType": "String"
										},
										"sink": {
											"name": "ptg_Price_Change",
											"type": "Double",
											"physicalType": "float"
										}
									},
									{
										"source": {
											"name": "WTD % Price Change",
											"type": "String",
											"physicalType": "String"
										},
										"sink": {
											"name": "WTD_ptg_Price_Change",
											"type": "Double",
											"physicalType": "float"
										}
									},
									{
										"source": {
											"name": "MTD % Price Change",
											"type": "String",
											"physicalType": "String"
										},
										"sink": {
											"name": "MTD_ptg_Price_Change",
											"type": "Double",
											"physicalType": "float"
										}
									},
									{
										"source": {
											"name": "QTD % Price Change",
											"type": "String",
											"physicalType": "String"
										},
										"sink": {
											"name": "QTD_ptg_Price_Change",
											"type": "Double",
											"physicalType": "float"
										}
									},
									{
										"source": {
											"name": "YTD % Price Change",
											"type": "String",
											"physicalType": "String"
										},
										"sink": {
											"name": "YTD_ptg_Price_Change",
											"type": "Double",
											"physicalType": "float"
										}
									},
									{
										"source": {
											"name": "12 Month % Price Change",
											"type": "String",
											"physicalType": "String"
										},
										"sink": {
											"name": "one_Year_ptg_Price_Change",
											"type": "Double",
											"physicalType": "float"
										}
									}
								],
								"typeConversion": true,
								"typeConversionSettings": {
									"allowDataTruncation": true,
									"treatBooleanAsNumber": false
								}
							}
						},
						"inputs": [
							{
								"referenceName": "InputExcel",
								"type": "DatasetReference",
								"parameters": {}
							}
						],
						"outputs": [
							{
								"referenceName": "SqlDB",
								"type": "DatasetReference",
								"parameters": {}
							}
						]
					},
					{
						"name": "Notebook1",
						"type": "DatabricksNotebook",
						"dependsOn": [
							{
								"activity": "Copy data1",
								"dependencyConditions": [
									"Succeeded"
								]
							}
						],
						"policy": {
							"timeout": "0.12:00:00",
							"retry": 0,
							"retryIntervalInSeconds": 30,
							"secureOutput": false,
							"secureInput": false
						},
						"userProperties": [],
						"typeProperties": {
							"notebookPath": "/Users/chen1421@e.ntu.edu.sg/testsql"
						},
						"linkedServiceName": {
							"referenceName": "AzureDatabricks1",
							"type": "LinkedServiceReference"
						}
					}
				],
				"policy": {
					"elapsedTimeMetric": {},
					"cancelAfter": {}
				},
				"annotations": []
			},
			"dependsOn": [
				"[concat(variables('factoryId'), '/datasets/InputExcel')]",
				"[concat(variables('factoryId'), '/datasets/SqlDB')]",
				"[concat(variables('factoryId'), '/linkedServices/AzureDatabricks1')]"
			]
		},
		{
			"name": "[concat(parameters('factoryName'), '/CSV')]",
			"type": "Microsoft.DataFactory/factories/datasets",
			"apiVersion": "2018-06-01",
			"properties": {
				"linkedServiceName": {
					"referenceName": "AzureBlobStorage1",
					"type": "LinkedServiceReference"
				},
				"annotations": [],
				"type": "DelimitedText",
				"typeProperties": {
					"location": {
						"type": "AzureBlobStorageLocation",
						"fileName": "test2.csv",
						"container": "excel"
					},
					"columnDelimiter": ",",
					"escapeChar": "\\",
					"firstRowAsHeader": true,
					"quoteChar": "\""
				},
				"schema": []
			},
			"dependsOn": [
				"[concat(variables('factoryId'), '/linkedServices/AzureBlobStorage1')]"
			]
		},
		{
			"name": "[concat(parameters('factoryName'), '/InputExcel')]",
			"type": "Microsoft.DataFactory/factories/datasets",
			"apiVersion": "2018-06-01",
			"properties": {
				"linkedServiceName": {
					"referenceName": "AzureFileStorage1",
					"type": "LinkedServiceReference"
				},
				"annotations": [],
				"type": "Excel",
				"typeProperties": {
					"sheetName": "Sheet 1",
					"location": {
						"type": "AzureFileStorageLocation"
					},
					"firstRowAsHeader": true
				},
				"schema": []
			},
			"dependsOn": [
				"[concat(variables('factoryId'), '/linkedServices/AzureFileStorage1')]"
			]
		},
		{
			"name": "[concat(parameters('factoryName'), '/SqlDB')]",
			"type": "Microsoft.DataFactory/factories/datasets",
			"apiVersion": "2018-06-01",
			"properties": {
				"linkedServiceName": {
					"referenceName": "outputSql",
					"type": "LinkedServiceReference"
				},
				"annotations": [],
				"type": "AzureSqlTable",
				"schema": [
					{
						"name": "Position_Scenario_Date_Adjusted",
						"type": "datetime",
						"precision": 23,
						"scale": 3
					},
					{
						"name": "FundShortName",
						"type": "varchar"
					},
					{
						"name": "Hierarchy3",
						"type": "varchar"
					},
					{
						"name": "Instrument_Subtype",
						"type": "varchar"
					},
					{
						"name": "BB_Yellow_Key",
						"type": "varchar"
					},
					{
						"name": "Description",
						"type": "varchar"
					},
					{
						"name": "Keystone_Broad_Sector",
						"type": "varchar"
					},
					{
						"name": "Keystone_Custom_Sector",
						"type": "varchar"
					},
					{
						"name": "GIC_Sector",
						"type": "varchar"
					},
					{
						"name": "GIC_Industry_Group",
						"type": "varchar"
					},
					{
						"name": "GIC_Industry",
						"type": "varchar"
					},
					{
						"name": "Exchange",
						"type": "varchar"
					},
					{
						"name": "Risk_Country",
						"type": "varchar"
					},
					{
						"name": "Country_of_Domicile",
						"type": "varchar"
					},
					{
						"name": "Country_Region",
						"type": "varchar"
					},
					{
						"name": "Exchange_Country_Name",
						"type": "varchar"
					},
					{
						"name": "Exchange_Country_Region",
						"type": "varchar"
					},
					{
						"name": "Notional_Quantity",
						"type": "int",
						"precision": 10
					},
					{
						"name": "Market_Price",
						"type": "float",
						"precision": 15
					},
					{
						"name": "Position_Instrument_Market_Price",
						"type": "float",
						"precision": 15
					},
					{
						"name": "LongShort_Position",
						"type": "varchar"
					},
					{
						"name": "NMV_excl_Cash_FX",
						"type": "float",
						"precision": 15
					},
					{
						"name": "GMV_excl_Cash_FX",
						"type": "float",
						"precision": 15
					},
					{
						"name": "PBD_NMV_excl_CashnFX",
						"type": "float",
						"precision": 15
					},
					{
						"name": "PBD_GMV_excl_CashnFX",
						"type": "float",
						"precision": 15
					},
					{
						"name": "Daily_PnL",
						"type": "float",
						"precision": 15
					},
					{
						"name": "AUM",
						"type": "int",
						"precision": 10
					},
					{
						"name": "Market_Capitalization_milUSD",
						"type": "float",
						"precision": 15
					},
					{
						"name": "Market_Cap",
						"type": "float",
						"precision": 15
					},
					{
						"name": "Daily_PnL_ptg_NAV",
						"type": "varchar"
					},
					{
						"name": "NMV_ptg_NAV",
						"type": "float",
						"precision": 15
					},
					{
						"name": "GMV_ptg_NAV",
						"type": "float",
						"precision": 15
					},
					{
						"name": "Beta_Adj_MV_MSCICN",
						"type": "float",
						"precision": 15
					},
					{
						"name": "Beta_Adj_MV_MSCI_ex_Japan",
						"type": "float",
						"precision": 15
					},
					{
						"name": "Beta_Adj_MV_MSCI_Asia",
						"type": "float",
						"precision": 15
					},
					{
						"name": "Beta_Adj_MV_SPX",
						"type": "float",
						"precision": 15
					},
					{
						"name": "Beta_MSCICN",
						"type": "float",
						"precision": 15
					},
					{
						"name": "Beta_MSCI_ex_Japan",
						"type": "float",
						"precision": 15
					},
					{
						"name": "Beta_MSCI_Asia",
						"type": "float",
						"precision": 15
					},
					{
						"name": "BetaSPX",
						"type": "float",
						"precision": 15
					},
					{
						"name": "Position_Age_From_Last_Trade_Date",
						"type": "int",
						"precision": 10
					},
					{
						"name": "Position_Age_From_First_Trade_Date",
						"type": "int",
						"precision": 10
					},
					{
						"name": "Custodian",
						"type": "varchar"
					},
					{
						"name": "Holding_Scenario",
						"type": "varchar"
					},
					{
						"name": "ptg_Price_Change",
						"type": "float",
						"precision": 15
					},
					{
						"name": "WTD_ptg_Price_Change",
						"type": "float",
						"precision": 15
					},
					{
						"name": "MTD_ptg_Price_Change",
						"type": "float",
						"precision": 15
					},
					{
						"name": "QTD_ptg_Price_Change",
						"type": "float",
						"precision": 15
					},
					{
						"name": "YTD_ptg_Price_Change",
						"type": "float",
						"precision": 15
					},
					{
						"name": "one_Year_ptg_Price_Change",
						"type": "float",
						"precision": 15
					}
				],
				"typeProperties": {
					"schema": "dbo",
					"table": "Enfusion"
				}
			},
			"dependsOn": [
				"[concat(variables('factoryId'), '/linkedServices/outputSql')]"
			]
		},
		{
			"name": "[concat(parameters('factoryName'), '/AzureBlobStorage1')]",
			"type": "Microsoft.DataFactory/factories/linkedServices",
			"apiVersion": "2018-06-01",
			"properties": {
				"annotations": [],
				"type": "AzureBlobStorage",
				"typeProperties": {
					"connectionString": "[parameters('AzureBlobStorage1_connectionString')]"
				}
			},
			"dependsOn": []
		},
		{
			"name": "[concat(parameters('factoryName'), '/AzureDatabricks1')]",
			"type": "Microsoft.DataFactory/factories/linkedServices",
			"apiVersion": "2018-06-01",
			"properties": {
				"annotations": [],
				"type": "AzureDatabricks",
				"typeProperties": {
					"domain": "https://adb-3402675344004964.4.azuredatabricks.net",
					"accessToken": {
						"type": "SecureString",
						"value": "[parameters('AzureDatabricks1_accessToken')]"
					},
					"existingClusterId": "[parameters('AzureDatabricks1_properties_typeProperties_existingClusterId')]"
				}
			},
			"dependsOn": []
		},
		{
			"name": "[concat(parameters('factoryName'), '/AzureFileStorage1')]",
			"type": "Microsoft.DataFactory/factories/linkedServices",
			"apiVersion": "2018-06-01",
			"properties": {
				"annotations": [],
				"type": "AzureFileStorage",
				"typeProperties": {
					"connectionString": "[parameters('AzureFileStorage1_connectionString')]",
					"fileShare": "azurefileshare"
				}
			},
			"dependsOn": []
		},
		{
			"name": "[concat(parameters('factoryName'), '/outputSql')]",
			"type": "Microsoft.DataFactory/factories/linkedServices",
			"apiVersion": "2018-06-01",
			"properties": {
				"annotations": [],
				"type": "AzureSqlDatabase",
				"typeProperties": {
					"connectionString": "[parameters('outputSql_connectionString')]"
				}
			},
			"dependsOn": []
		},
		{
			"name": "[concat(parameters('factoryName'), '/trigger1')]",
			"type": "Microsoft.DataFactory/factories/triggers",
			"apiVersion": "2018-06-01",
			"properties": {
				"annotations": [],
				"runtimeState": "Stopped",
				"pipelines": [
					{
						"pipelineReference": {
							"referenceName": "pipeline1",
							"type": "PipelineReference"
						},
						"parameters": {}
					}
				],
				"type": "ScheduleTrigger",
				"typeProperties": {
					"recurrence": {
						"frequency": "Minute",
						"interval": 5,
						"startTime": "2022-08-22T14:46:00",
						"endTime": "2022-08-23T00:59:00",
						"timeZone": "Singapore Standard Time"
					}
				}
			},
			"dependsOn": [
				"[concat(variables('factoryId'), '/pipelines/pipeline1')]"
			]
		}
	]
}